<?xml version="1.0" encoding="UTF-8"?>
<UnityGameFramework>
  <BuildSettings>
    <DefaultScenes>
      <DefaultScene Name="Assets/GameMain/Launcher.unity" />
      <DefaultScene Name="Assets/GameMain/BaseAssets/Scenes/Login.unity" />
      <DefaultScene Name="Assets/GameMain/BaseAssets/Scenes/Main.unity" />
      <DefaultScene Name="Assets/GameMain/BaseAssets/Scenes/Fight.unity" />
    </DefaultScenes>
    <SearchScenePaths>
      <SearchScenePath Path="Assets/GameMain" />
    </SearchScenePaths>
  </BuildSettings>
</UnityGameFramework>